HDDFeaturesX/__init__.py
HDDFeaturesX/discernibleScore.py
HDDFeaturesX/fastFeatureSelectionDS.py
HDDFeaturesX/increDiscernibleScore.py
HDDFeaturesX/increFeaSltDSFilterSam.py
HDDFeaturesX/increFeatureSelectionDS.py
HDDFeaturesX/partition_fold.py
HDDFeaturesX-0.1.3.dist-info/METADATA
HDDFeaturesX-0.1.3.dist-info/WHEEL
HDDFeaturesX-0.1.3.dist-info/top_level.txt
HDDFeaturesX-0.1.3.dist-info/RECORD
