Metadata-Version: 2.1
Name: HDDFeaturesX
Version: 0.1.3
Summary: A library for feature selection in high-dimensional datasets
Home-page: https://github.com/saiddddd/HDDFeaturesX
Author: Said Al Afghani Edsa, Khamron Sunat, P.hD
Author-email: saidalafghani.dumai@gmail.com
Classifier: Programming Language :: Python :: 3
Classifier: License :: OSI Approved :: MIT License
Classifier: Operating System :: OS Independent
Requires-Python: >=3.6
